odoo/addons/stock_available_to_promise_release_shipment_advice/README.rst
odoo/addons/stock_available_to_promise_release_shipment_advice/__init__.py
odoo/addons/stock_available_to_promise_release_shipment_advice/__manifest__.py
odoo/addons/stock_available_to_promise_release_shipment_advice/i18n/it.po
odoo/addons/stock_available_to_promise_release_shipment_advice/i18n/stock_available_to_promise_release_shipment_advice.pot
odoo/addons/stock_available_to_promise_release_shipment_advice/models/__init__.py
odoo/addons/stock_available_to_promise_release_shipment_advice/models/stock_move.py
odoo/addons/stock_available_to_promise_release_shipment_advice/readme/CONTRIBUTORS.rst
odoo/addons/stock_available_to_promise_release_shipment_advice/readme/DESCRIPTION.rst
odoo/addons/stock_available_to_promise_release_shipment_advice/static/description/icon.png
odoo/addons/stock_available_to_promise_release_shipment_advice/static/description/index.html
odoo/addons/stock_available_to_promise_release_shipment_advice/tests/__init__.py
odoo/addons/stock_available_to_promise_release_shipment_advice/tests/test_unrelease_cancel.py
odoo14_addon_stock_available_to_promise_release_shipment_advice-14.0.1.0.1.dev6.dist-info/METADATA
odoo14_addon_stock_available_to_promise_release_shipment_advice-14.0.1.0.1.dev6.dist-info/WHEEL
odoo14_addon_stock_available_to_promise_release_shipment_advice-14.0.1.0.1.dev6.dist-info/top_level.txt
odoo14_addon_stock_available_to_promise_release_shipment_advice-14.0.1.0.1.dev6.dist-info/RECORD
