Metadata-Version: 2.1
Name: odoo14-addon-stock_available_to_promise_release_shipment_advice
Version: 14.0.1.0.1.dev6
Summary: Glue module between release of operations and shipment advice
Home-page: https://github.com/OCA/wms
Author: BCIM, Odoo Community Association (OCA)
Author-email: support@odoo-community.org
License: AGPL-3
Classifier: Programming Language :: Python
Classifier: Framework :: Odoo
Classifier: Framework :: Odoo :: 14.0
Classifier: License :: OSI Approved :: GNU Affero General Public License v3
Classifier: Development Status :: 4 - Beta
Requires-Python: >=3.6
Requires-Dist: odoo14-addon-shipment-advice
Requires-Dist: odoo14-addon-stock-available-to-promise-release
Requires-Dist: odoo<14.1dev,>=14.0a
